CHANGES.txt
MANIFEST.in
README.md
setup.py
docs/HISTORY.txt
wheelcms_project/__init__.py
wheelcms_project/urls.py
wheelcms_project.egg-info/PKG-INFO
wheelcms_project.egg-info/SOURCES.txt
wheelcms_project.egg-info/dependency_links.txt
wheelcms_project.egg-info/namespace_packages.txt
wheelcms_project.egg-info/not-zip-safe
wheelcms_project.egg-info/requires.txt
wheelcms_project.egg-info/top_level.txt
wheelcms_project/settings/__init__.py
wheelcms_project/settings/local.py
wheelcms_project/settings/production.py
wheelcms_project/settings/test.py
wheelcms_project/settings/base/__init__.py
wheelcms_project/settings/base/settings_admin.py
wheelcms_project/settings/base/settings_database.py
wheelcms_project/settings/base/settings_django.py
wheelcms_project/settings/base/settings_locale.py
wheelcms_project/settings/base/settings_logging.py
wheelcms_project/settings/base/settings_mail.py
wheelcms_project/settings/base/settings_misc.py
wheelcms_project/settings/base/settings_paths.py
wheelcms_project/settings/base/settings_redis.py
wheelcms_project/settings/base/settings_search.py
wheelcms_project/settings/base/util.py
wheelcms_project/static/.gitignore