Metadata-Version: 1.1
Name: wheelcms-project
Version: 0.8.1
Summary: WheelCMS project package
Home-page: http://github.com/wheelcms/wheelcms_project
Author: Ivo van der Wijk
Author-email: wheelcms@in.m3r.nl
License: BSD
Platform: UNKNOWN
Classifier: Programming Language :: Python
